LICENSE
MANIFEST.in
README.rst
VERSION
classifiers.txt
requirements-test.txt
requirements.txt
setup.py
ddec/__init__.py
ddec/decorators.py
ddec/tests/__init__.py
ddec/tests/decorators.py
dtype_decorate.egg-info/PKG-INFO
dtype_decorate.egg-info/SOURCES.txt
dtype_decorate.egg-info/dependency_links.txt
dtype_decorate.egg-info/not-zip-safe
dtype_decorate.egg-info/top_level.txt