Metadata-Version: 1.1
Name: dtype-decorate
Version: 0.1.1
Summary: data type check and conversion decorators
Home-page: UNKNOWN
Author: Mirko Maelicke
Author-email: mirko.maelicke@kit.edu
License: MIT
Platform: UNKNOWN
Classifier: Development Status :: 4 - Beta
Classifier: Intended Audience :: Science/Research
Classifier: License :: OSI Approved :: MIT License
Classifier: Natural Language :: English
Classifier: Programming Language :: Python :: 3.3
Classifier: Programming Language :: Python :: 3.4
Classifier: Programming Language :: Python :: 3.5
Classifier: Programming Language :: Python :: 3.6
